ml_easy/__init__.py
ml_easy/recipes/__init__.py
ml_easy/recipes/_typing.py
ml_easy/recipes/classification/__init__.py
ml_easy/recipes/classification/v1/__init__.py
ml_easy/recipes/classification/v1/config.py
ml_easy/recipes/classification/v1/recipe.py
ml_easy/recipes/classification/v1/steps.py
ml_easy/recipes/constants.py
ml_easy/recipes/enum.py
ml_easy/recipes/env_vars.py
ml_easy/recipes/exceptions.py
ml_easy/recipes/interfaces/__init__.py
ml_easy/recipes/interfaces/config.py
ml_easy/recipes/interfaces/recipe.py
ml_easy/recipes/interfaces/step.py
ml_easy/recipes/io/RecipeYAMLoader.py
ml_easy/recipes/io/__init__.py
ml_easy/recipes/steps/__init__.py
ml_easy/recipes/steps/cards_config.py
ml_easy/recipes/steps/evaluate/__init__.py
ml_easy/recipes/steps/evaluate/evaluate.py
ml_easy/recipes/steps/evaluate/score.py
ml_easy/recipes/steps/ingest/__init__.py
ml_easy/recipes/steps/ingest/datasets.py
ml_easy/recipes/steps/ingest/ingest.py
ml_easy/recipes/steps/register/__init__.py
ml_easy/recipes/steps/register/mlflow_source/__init__.py
ml_easy/recipes/steps/register/mlflow_source/sql_table_dataset_source.py
ml_easy/recipes/steps/register/register_.py
ml_easy/recipes/steps/register/registry.py
ml_easy/recipes/steps/split/__init__.py
ml_easy/recipes/steps/split/split.py
ml_easy/recipes/steps/split/splitter.py
ml_easy/recipes/steps/steps_config.py
ml_easy/recipes/steps/train/__init__.py
ml_easy/recipes/steps/train/models.py
ml_easy/recipes/steps/train/train.py
ml_easy/recipes/steps/transform/__init__.py
ml_easy/recipes/steps/transform/filters.py
ml_easy/recipes/steps/transform/formatter/__init__.py
ml_easy/recipes/steps/transform/formatter/formatter.py
ml_easy/recipes/steps/transform/transform.py
ml_easy/recipes/steps/transform/transformer.py
ml_easy/recipes/utils.py
ml_easy-0.1.2.dist-info/METADATA
ml_easy-0.1.2.dist-info/WHEEL
ml_easy-0.1.2.dist-info/RECORD
