Metadata-Version: 2.1
Name: ml-easy
Version: 0.1.2
Summary: 
Author: jalal
Author-email: jalalkhaldi3@gmail.com
Requires-Python: >=3.12,<4.0
Classifier: Programming Language :: Python :: 3
Classifier: Programming Language :: Python :: 3.12
Requires-Dist: jinja2 (>=3.1.4,<4.0.0)
Requires-Dist: jupyter (>=1.0.0,<2.0.0)
Requires-Dist: mlflow (>=2.15.0,<3.0.0)
Requires-Dist: mypy (>=1.11.0,<2.0.0)
Requires-Dist: nltk (==3.8.1)
Requires-Dist: pandas (>=2.2.2,<3.0.0)
Requires-Dist: pandas-stubs (>=2.2.2.240807,<3.0.0.0)
Requires-Dist: pickledb (>=0.9.2,<0.10.0)
Requires-Dist: polars (>=1.2.1,<2.0.0)
Requires-Dist: pre-commit (>=3.8.0,<4.0.0)
Requires-Dist: psycopg2-binary (>=2.9.9,<3.0.0)
Requires-Dist: pydantic (>=2.8.2,<3.0.0)
Requires-Dist: pytest (>=8.3.2,<9.0.0)
Requires-Dist: pyyaml (>=6.0.1,<7.0.0)
Requires-Dist: regex (>=2024.7.24,<2025.0.0)
Requires-Dist: scikit-learn (>=1.5.1,<2.0.0)
Requires-Dist: starlette (>=0.38.2,<0.39.0)
Requires-Dist: typeguard (>=4.3.0,<5.0.0)
Requires-Dist: types-pyyaml (>=6.0.12.20240808,<7.0.0.0)
Requires-Dist: types-regex (>=2024.7.24.20240726,<2025.0.0.0)
Requires-Dist: types-requests (>=2.32.0.20240712,<3.0.0.0)
